ausfin/__init__.py
ausfin/cli.py
ausfin/sources.py
ausfin-0.2.3.dist-info/METADATA
ausfin-0.2.3.dist-info/RECORD
ausfin-0.2.3.dist-info/WHEEL
ausfin-0.2.3.dist-info/entry_points.txt
ausfin-0.2.3.dist-info/top_level.txt
