Metadata-Version: 2.1
Name: ausfin
Version: 0.2.3
Summary: Account balance scraping for Australian financial institutions
Home-page: https://github.com/cmbrad/ausfin-scrape
Author: Chris Braldey
Author-email: chris.bradley@cy.id.au
License: UNKNOWN
Platform: UNKNOWN
Provides-Extra: test
Requires-Dist: click (<6.8,>=6.7)
Requires-Dist: selenium (<3.12,>=3.11)
Requires-Dist: tabulate (<0.9,>=0.8)
Requires-Dist: requests (<2.19,>=2.18)
Provides-Extra: test
Requires-Dist: pytest (<3.6,>=3.5); extra == 'test'
Requires-Dist: pytest-flake8 (<1.1,>=1.0); extra == 'test'
